Metadata-Version: 2.4
Name: idp_authentication
Version: 0.2.10
Summary: IDP Authentication - Hexagonal Architecture Implementation
Project-URL: Homepage, https://github.com/CardoAI/idp-authentication
Project-URL: Bug Tracker, https://github.com/CardoAI/idp-authentication/issues
Author-email: Lirim Shala <lirim.shala@cardoai.com>, Klajdi Çaushi <klajdi.caushi@cardoai.com>
License-File: LICENSE
Classifier: Intended Audience :: Information Technology
Classifier: Intended Audience :: System Administrators
Classifier: Operating System :: OS Independent
Classifier: Programming Language :: Python
Classifier: Programming Language :: Python :: 3.10
Classifier: Programming Language :: Python :: 3.11
Requires-Python: >=3.10
Requires-Dist: dependency-injector>=4.41.0
Requires-Dist: pydantic>=1.10.4
Requires-Dist: sqlalchemy>=1.4.46
Provides-Extra: all
Requires-Dist: dependency-injector>=4.41.0; extra == 'all'
Requires-Dist: pydantic>=1.10.4; extra == 'all'
Requires-Dist: sqlalchemy>=1.4.46; extra == 'all'
Provides-Extra: docs
Requires-Dist: mkdocs-material==8.5.11; extra == 'docs'
Requires-Dist: mkdocstrings[python]==0.19.1; extra == 'docs'
Provides-Extra: test
Requires-Dist: autoflake==2.0.0; extra == 'test'
Requires-Dist: black>=22.10.0; extra == 'test'
Requires-Dist: faker==15.3.4; extra == 'test'
Requires-Dist: isort==5.11.3; extra == 'test'
Requires-Dist: pytest-cov==4.0.0; extra == 'test'
Requires-Dist: pytest==7.2.0; extra == 'test'
